{
  "name": "mitigation_cb2024-250mt",
  "data": [
    {
      "seriesName": "INDBKE",
      "seriesValues": [
        [
          2018,
          0.010747171378822199
        ],
        [
          2019,
          0.0211879579483058
        ],
        [
          2023,
          0.0003303179794410992
        ],
        [
          2024,
          0.00043336969887329524
        ],
        [
          2025,
          0.000524585924811837
        ],
        [
          2026,
          0.000604802303776919
        ],
        [
          2027,
          0.0006746448162004107
        ],
        [
          2028,
          0.0007345749329672822
        ],
        [
          2029,
          0.0007847540102811185
        ],
        [
          2030,
          0.0008256906200970327
        ],
        [
          2031,
          0.0008674850871319587
        ],
        [
          2032,
          0.0008994731754336067
        ],
        [
          2033,
          0.0009218275410411197
        ],
        [
          2034,
          0.0009347584569503199
        ],
        [
          2035,
          0.0009388034348439578
        ],
        [
          2036,
          0.0009344105351923044
        ],
        [
          2037,
          0.0009220581747835336
        ],
        [
          2038,
          0.0009021757930636171
        ],
        [
          2039,
          0.0008754381634410944
        ],
        [
          2040,
          0.000842410248887024
        ],
        [
          2041,
          0.0008035569428570835
        ],
        [
          2042,
          0.0007595145568964833
        ],
        [
          2043,
          0.0007110272844209055
        ],
        [
          2044,
          0.0006592576347852039
        ],
        [
          2045,
          0.0006048780963155148
        ],
        [
          2046,
          0.0005484583804373204
        ],
        [
          2047,
          0.0004908099763857079
        ],
        [
          2048,
          0.0004326367875748983
        ],
        [
          2049,
          0.0003750603678687225
        ],
        [
          2050,
          0.000318616857912679
        ],
        [
          2051,
          2.035304431167781e-06
        ]
      ]
    },
    {
      "seriesName": "INDDST",
      "seriesValues": [
        [
          2018,
          0.6168891208547258
        ],
        [
          2019,
          1.203957851306002
        ],
        [
          2020,
          1.2624890679143235
        ],
        [
          2021,
          1.2807035685458403
        ],
        [
          2022,
          0.7478865202888874
        ],
        [
          2023,
          0.7086819999656406
        ],
        [
          2024,
          0.6714873267964763
        ],
        [
          2025,
          0.6361107753102692
        ],
        [
          2026,
          0.602336930347919
        ],
        [
          2027,
          0.4525105777765089
        ],
        [
          2028,
          0.4110321134921443
        ],
        [
          2029,
          0.37214668180186433
        ],
        [
          2030,
          0.33578140914449367
        ],
        [
          2031,
          0.300115210612187
        ],
        [
          2032,
          0.2669164155942561
        ],
        [
          2033,
          0.2360254781738195
        ],
        [
          2034,
          0.2073389761625399
        ],
        [
          2035,
          0.1808362012947825
        ],
        [
          2036,
          0.1564614350116877
        ],
        [
          2037,
          0.1341576297645165
        ],
        [
          2038,
          0.1138552002499478
        ],
        [
          2039,
          0.0955101292659595
        ],
        [
          2040,
          0.0790522458835831
        ],
        [
          2041,
          0.0643975761633271
        ],
        [
          2042,
          0.0514743387144942
        ],
        [
          2043,
          0.0402095982754393
        ],
        [
          2044,
          0.030539737707637602
        ],
        [
          2045,
          0.0223594398913549
        ],
        [
          2046,
          0.015558536411849304
        ],
        [
          2047,
          0.010033503163209364
        ],
        [
          2048,
          0.005673698591199369
        ],
        [
          2049,
          0.0023693717409630044
        ]
      ]
    },
    {
      "seriesName": "INDELC",
      "seriesValues": [
        [
          2018,
          0.7823282370306878
        ],
        [
          2019,
          1.073055159349604
        ],
        [
          2020,
          1.020176162123043
        ],
        [
          2021,
          1.0203578994860412
        ],
        [
          2022,
          0.5958401811248795
        ],
        [
          2023,
          0.5645900021988948
        ],
        [
          2024,
          0.534957909937632
        ],
        [
          2025,
          0.506774268491356
        ],
        [
          2026,
          0.4798675123300046
        ],
        [
          2027,
          0.45417852303686923
        ],
        [
          2028,
          0.4294548558307535
        ],
        [
          2029,
          0.4054430718724368
        ],
        [
          2030,
          0.3821555959907857
        ],
        [
          2031,
          0.3595631461459373
        ],
        [
          2032,
          0.3375548591012601
        ],
        [
          2033,
          0.3160475774328645
        ],
        [
          2034,
          0.29498810002878517
        ],
        [
          2035,
          0.2744345654723816
        ],
        [
          2036,
          0.2544047978808856
        ],
        [
          2037,
          0.2349197779373153
        ],
        [
          2038,
          0.2159836962378884
        ],
        [
          2039,
          0.1976551801693727
        ],
        [
          2040,
          0.179956772125816
        ],
        [
          2041,
          0.1628861212763119
        ],
        [
          2042,
          0.1464743948309481
        ],
        [
          2043,
          0.1307668200138156
        ],
        [
          2044,
          0.11587413381329689
        ],
        [
          2045,
          0.1018058076487578
        ],
        [
          2046,
          0.0885531770332271
        ],
        [
          2047,
          0.0761464431197627
        ],
        [
          2048,
          0.0645951981826273
        ],
        [
          2049,
          0.0539677402605786
        ],
        [
          2050,
          0.0442421363500232
        ],
        [
          2051,
          0.0353876519690616
        ]
      ]
    },
    {
      "seriesName": "INDGAS",
      "seriesValues": [
        [
          2018,
          0.4740190013470681
        ],
        [
          2019,
          0.6100881537443146
        ],
        [
          2020,
          0.6316100013787044
        ],
        [
          2021,
          0.606948338616095
        ],
        [
          2022,
          0.3427346939142496
        ],
        [
          2023,
          0.3085618833687666
        ],
        [
          2024,
          0.2946190387265914
        ],
        [
          2025,
          0.2726288480780075
        ],
        [
          2026,
          0.2458668756842202
        ],
        [
          2027,
          0.2144479980930743
        ],
        [
          2028,
          0.1947910442572105
        ],
        [
          2029,
          0.176362960935088
        ],
        [
          2030,
          0.1591291967988751
        ],
        [
          2031,
          0.1422315810815744
        ],
        [
          2032,
          0.1264981394265546
        ],
        [
          2033,
          0.1118584143341291
        ],
        [
          2034,
          0.0982633925980918
        ],
        [
          2035,
          0.0857032612944171
        ],
        [
          2036,
          0.0741516156792541
        ],
        [
          2037,
          0.0635814202780811
        ],
        [
          2038,
          0.053959698390139
        ],
        [
          2039,
          0.0452655908544528
        ],
        [
          2040,
          0.0374658434576773
        ],
        [
          2041,
          0.0305206603860422
        ],
        [
          2042,
          0.024396024192775298
        ],
        [
          2043,
          0.0190573709499192
        ],
        [
          2044,
          0.0144745535463708
        ],
        [
          2045,
          0.010597661596108752
        ],
        [
          2046,
          0.007374485579365662
        ],
        [
          2047,
          0.004755965041360226
        ],
        [
          2048,
          0.0026896663216765897
        ],
        [
          2049,
          0.0011235791654001155
        ],
        [
          2051,
          0.009056166754547451
        ]
      ]
    },
    {
      "seriesName": "INDKER",
      "seriesValues": [
        [
          2018,
          0.0105548323444577
        ],
        [
          2019,
          0.0069132453720249
        ],
        [
          2020,
          0.008390077125452134
        ],
        [
          2021,
          0.007348466821443233
        ],
        [
          2022,
          0.004274330857737893
        ],
        [
          2023,
          0.0037358924823047346
        ],
        [
          2024,
          0.0034194286152849297
        ],
        [
          2025,
          0.0031252321751358016
        ],
        [
          2026,
          0.0028512317882135674
        ],
        [
          2027,
          0.0025963756784418432
        ],
        [
          2028,
          0.0023583842651107396
        ],
        [
          2029,
          0.002135270933102962
        ],
        [
          2030,
          0.0019266163942430162
        ],
        [
          2031,
          0.0017220134503365282
        ],
        [
          2032,
          0.0015315269428430574
        ],
        [
          2033,
          0.0013542818906917729
        ],
        [
          2034,
          0.001189684981079346
        ],
        [
          2035,
          0.0010376175473833604
        ],
        [
          2036,
          0.0008977600231215339
        ],
        [
          2037,
          0.0007697849869877824
        ],
        [
          2038,
          0.0006532932396012168
        ],
        [
          2039,
          0.0005480322389123115
        ],
        [
          2040,
          0.00045359942169147916
        ],
        [
          2041,
          0.00036951314195727907
        ],
        [
          2042,
          0.0002953612075891915
        ],
        [
          2043,
          0.0002307250627804666
        ],
        [
          2044,
          0.00017523978661346305
        ],
        [
          2045,
          0.00012830122866922634
        ],
        [
          2046,
          8.927735175502338e-05
        ],
        [
          2047,
          5.757438176729331e-05
        ],
        [
          2048,
          3.2557526843394215e-05
        ],
        [
          2049,
          1.3597654586997786e-05
        ],
        [
          2051,
          0.0002519321071034445
        ]
      ]
    },
    {
      "seriesName": "INDLPG",
      "seriesValues": [
        [
          2018,
          0.0038156799027501804
        ],
        [
          2019,
          0.0007000645866461083
        ],
        [
          2020,
          0.0006430798592933371
        ],
        [
          2021,
          0.000699854294979452
        ],
        [
          2022,
          0.00040863411345011313
        ],
        [
          2023,
          0.0003872579910981481
        ],
        [
          2024,
          0.0003669306356202741
        ],
        [
          2025,
          0.00034759915810569377
        ],
        [
          2026,
          0.0003291434813457054
        ],
        [
          2027,
          0.00031152288293651064
        ],
        [
          2028,
          0.00029456433793971943
        ],
        [
          2029,
          0.0002780943959544198
        ],
        [
          2030,
          0.00026211880968785516
        ],
        [
          2031,
          0.000246599225577317
        ],
        [
          2032,
          0.00023150384790930604
        ],
        [
          2033,
          0.00021675210752092184
        ],
        [
          2034,
          0.00020230751290806507
        ],
        [
          2035,
          0.00018820993711525334
        ],
        [
          2036,
          0.00017447159715529441
        ],
        [
          2037,
          0.00016110690239201961
        ],
        [
          2038,
          0.00014811873070656097
        ],
        [
          2039,
          0.00013554730152087388
        ],
        [
          2040,
          0.00012340808045469324
        ],
        [
          2041,
          0.00011169942432390452
        ],
        [
          2042,
          0.00010044275862223994
        ],
        [
          2043,
          8.966907985777821e-05
        ],
        [
          2044,
          7.945433127395165e-05
        ],
        [
          2045,
          6.980501721854133e-05
        ],
        [
          2046,
          6.0715181986546496e-05
        ],
        [
          2047,
          5.220549365094772e-05
        ],
        [
          2048,
          4.4282702605188704e-05
        ],
        [
          2049,
          3.6993632529482266e-05
        ],
        [
          2050,
          2.908583795990514e-05
        ],
        [
          2051,
          2.4189202272141624e-05
        ]
      ]
    },
    {
      "seriesName": "INDBGS",
      "seriesValues": [
        [
          2019,
          0.0010861394446545923
        ],
        [
          2022,
          0.011694107820481935
        ],
        [
          2023,
          0.027287682586314498
        ],
        [
          2024,
          0.0236037074378458
        ],
        [
          2025,
          0.028828699065439
        ],
        [
          2026,
          0.0395850348805155
        ],
        [
          2027,
          0.0557226712825852
        ],
        [
          2028,
          0.0606726111993972
        ],
        [
          2029,
          0.0648171486043447
        ],
        [
          2030,
          0.06819822386998671
        ],
        [
          2031,
          0.0716504860477006
        ],
        [
          2032,
          0.0742925474200068
        ],
        [
          2033,
          0.0761389096420175
        ],
        [
          2034,
          0.0772069398317712
        ],
        [
          2035,
          0.0775410338973072
        ],
        [
          2036,
          0.0771781991189665
        ],
        [
          2037,
          0.0761579510732171
        ],
        [
          2038,
          0.074515759188102
        ],
        [
          2039,
          0.0723073565352198
        ],
        [
          2040,
          0.0695794063674301
        ],
        [
          2041,
          0.0663703061296719
        ],
        [
          2042,
          0.0627326127295529
        ],
        [
          2043,
          0.0587277930049546
        ],
        [
          2044,
          0.0544518647100442
        ],
        [
          2045,
          0.049960372178961904
        ],
        [
          2046,
          0.045300370966114195
        ],
        [
          2047,
          0.040538886368384104
        ],
        [
          2048,
          0.035734057864769
        ],
        [
          2049,
          0.030978522037127698
        ],
        [
          2050,
          0.0263169241921875
        ],
        [
          2051,
          0.011993797515861514
        ]
      ]
    },
    {
      "seriesName": "INDBDL",
      "seriesValues": [
        [
          2027,
          0.1175814652358095
        ],
        [
          2028,
          0.1280263919282159
        ],
        [
          2029,
          0.1367718535669318
        ],
        [
          2030,
          0.1439063153405761
        ],
        [
          2031,
          0.1511910025417611
        ],
        [
          2032,
          0.1567660649375148
        ],
        [
          2033,
          0.1606621078774663
        ],
        [
          2034,
          0.1629157779631306
        ],
        [
          2035,
          0.1636207556876041
        ],
        [
          2036,
          0.1628551316170139
        ],
        [
          2037,
          0.1607022873959848
        ],
        [
          2038,
          0.1572370680131352
        ],
        [
          2039,
          0.1525770771795587
        ],
        [
          2040,
          0.1468207796996947
        ],
        [
          2041,
          0.1400491987114563
        ],
        [
          2042,
          0.132373235451401
        ],
        [
          2043,
          0.1239225923286667
        ],
        [
          2044,
          0.1148998780921009
        ],
        [
          2045,
          0.1054222977013609
        ],
        [
          2046,
          0.0955891443108017
        ],
        [
          2047,
          0.0855418489884404
        ],
        [
          2048,
          0.0754030926953005
        ],
        [
          2049,
          0.0653683502804424
        ],
        [
          2050,
          0.0555318368328197
        ],
        [
          2051,
          0.0444178174100109
        ]
      ]
    }
  ]
}