{
  "name": "mitigation_cb2024-350mt",
  "data": [
    {
      "seriesName": "INDBKE",
      "seriesValues": [
        [
          2018,
          0.0107649770310114
        ],
        [
          2019,
          0.0212933449425032
        ],
        [
          2024,
          0.00043325771084472286
        ],
        [
          2025,
          0.0005245532648866279
        ],
        [
          2026,
          0.0006048282625518522
        ],
        [
          2027,
          0.0006746717103421469
        ],
        [
          2028,
          0.0007346027453702153
        ],
        [
          2029,
          0.0007847815914019612
        ],
        [
          2030,
          0.0008257224727132995
        ],
        [
          2031,
          0.0008665070200568265
        ],
        [
          2032,
          0.0008987338238011178
        ],
        [
          2033,
          0.000921232159841149
        ],
        [
          2034,
          0.0009342597588871248
        ],
        [
          2035,
          0.0009383742958389653
        ],
        [
          2036,
          0.0009340380578357671
        ],
        [
          2037,
          0.0009217289790732658
        ],
        [
          2038,
          0.0009018807343977234
        ],
        [
          2039,
          0.0008751706716140262
        ],
        [
          2040,
          0.0008421654290591985
        ],
        [
          2041,
          0.0008033364662621972
        ],
        [
          2042,
          0.000759313640648424
        ],
        [
          2043,
          0.0007108422949282576
        ],
        [
          2044,
          0.0006590856957091599
        ],
        [
          2045,
          0.0006047168343057818
        ],
        [
          2046,
          0.0005483057017406875
        ],
        [
          2047,
          0.0004906638743118127
        ],
        [
          2048,
          0.0004321427311144126
        ],
        [
          2049,
          0.0003745253454867091
        ],
        [
          2050,
          0.00031712928245703495
        ],
        [
          2051,
          0.00025360078804065724
        ]
      ]
    },
    {
      "seriesName": "INDDST",
      "seriesValues": [
        [
          2018,
          0.6168891021882408
        ],
        [
          2019,
          1.203957828354333
        ],
        [
          2020,
          1.262488800363034
        ],
        [
          2021,
          1.2807035878095778
        ],
        [
          2022,
          0.7478862987835709
        ],
        [
          2023,
          0.708680262890929
        ],
        [
          2024,
          0.671485578816226
        ],
        [
          2025,
          0.6361090209065037
        ],
        [
          2026,
          0.49692841241504887
        ],
        [
          2027,
          0.45251057545398987
        ],
        [
          2028,
          0.4110321249585417
        ],
        [
          2029,
          0.3721466982451818
        ],
        [
          2030,
          0.3357814171663999
        ],
        [
          2031,
          0.300125845821829
        ],
        [
          2032,
          0.2669260761001311
        ],
        [
          2033,
          0.2360345424993069
        ],
        [
          2034,
          0.2073474342238135
        ],
        [
          2035,
          0.1808440725494842
        ],
        [
          2036,
          0.1564687347515128
        ],
        [
          2037,
          0.1341643510480878
        ],
        [
          2038,
          0.1138613901915686
        ],
        [
          2039,
          0.0955157972948556
        ],
        [
          2040,
          0.07905740330167389
        ],
        [
          2041,
          0.0644022404936905
        ],
        [
          2042,
          0.0514785362603994
        ],
        [
          2043,
          0.040213347019600096
        ],
        [
          2044,
          0.0305430719397047
        ],
        [
          2045,
          0.0223623812970576
        ],
        [
          2046,
          0.015561111443549257
        ],
        [
          2047,
          0.01003578748866308
        ],
        [
          2048,
          0.0056765523010147015
        ],
        [
          2049,
          0.0023709536814426582
        ]
      ]
    },
    {
      "seriesName": "INDELC",
      "seriesValues": [
        [
          2018,
          0.7823105390402761
        ],
        [
          2019,
          1.0729489785869843
        ],
        [
          2020,
          1.020176159382166
        ],
        [
          2021,
          1.0203579407089522
        ],
        [
          2022,
          0.5958401405422509
        ],
        [
          2023,
          0.5645900042052016
        ],
        [
          2024,
          0.5349579199481854
        ],
        [
          2025,
          0.5067742852419169
        ],
        [
          2026,
          0.4798675215126476
        ],
        [
          2027,
          0.4541785321819845
        ],
        [
          2028,
          0.4294548658196225
        ],
        [
          2029,
          0.4054430818115377
        ],
        [
          2030,
          0.3821556090108745
        ],
        [
          2031,
          0.3595530100504267
        ],
        [
          2032,
          0.3375548075726293
        ],
        [
          2033,
          0.316038673352998
        ],
        [
          2034,
          0.2949797927976328
        ],
        [
          2035,
          0.2744268413448421
        ],
        [
          2036,
          0.2543976409180656
        ],
        [
          2037,
          0.23491974414201158
        ],
        [
          2038,
          0.2159836436640636
        ],
        [
          2039,
          0.197655121470077
        ],
        [
          2040,
          0.1799567290749342
        ],
        [
          2041,
          0.162886084972004
        ],
        [
          2042,
          0.1464743603273392
        ],
        [
          2043,
          0.130766785039708
        ],
        [
          2044,
          0.1158741028056817
        ],
        [
          2045,
          0.1018057789716147
        ],
        [
          2046,
          0.08855315047141771
        ],
        [
          2047,
          0.0761464208938054
        ],
        [
          2048,
          0.0645951589529894
        ],
        [
          2049,
          0.053967696078265896
        ],
        [
          2050,
          0.0442420873501565
        ],
        [
          2051,
          0.0353876213871481
        ]
      ]
    },
    {
      "seriesName": "INDGAS",
      "seriesValues": [
        [
          2018,
          0.4740190138733892
        ],
        [
          2019,
          0.6100881645184021
        ],
        [
          2020,
          0.631609994160178
        ],
        [
          2021,
          0.6069483577821606
        ],
        [
          2022,
          0.342702925208308
        ],
        [
          2023,
          0.308562483122842
        ],
        [
          2024,
          0.2945639841995456
        ],
        [
          2025,
          0.2726196424511398
        ],
        [
          2026,
          0.2498301444262018
        ],
        [
          2027,
          0.214448032345156
        ],
        [
          2028,
          0.1947910649863226
        ],
        [
          2029,
          0.1763629843889872
        ],
        [
          2030,
          0.1591292082912795
        ],
        [
          2031,
          0.1684245549673456
        ],
        [
          2032,
          0.1541094691555727
        ],
        [
          2033,
          0.1406399887609602
        ],
        [
          2034,
          0.1276119164751895
        ],
        [
          2035,
          0.1154638910842091
        ],
        [
          2036,
          0.1041637607655546
        ],
        [
          2037,
          0.0937263798470095
        ],
        [
          2038,
          0.0837082063415427
        ],
        [
          2039,
          0.0737148691602668
        ],
        [
          2040,
          0.0657585333640963
        ],
        [
          2041,
          0.030524537765542502
        ],
        [
          2042,
          0.0243972330448961
        ],
        [
          2043,
          0.0190580999089058
        ],
        [
          2044,
          0.0144750811904472
        ],
        [
          2045,
          0.010598122896192644
        ],
        [
          2046,
          0.007374899465379585
        ],
        [
          2047,
          0.004756342759789169
        ],
        [
          2048,
          0.018737421492426753
        ],
        [
          2049,
          0.016079586235544317
        ],
        [
          2050,
          0.013029549376737446
        ],
        [
          2051,
          0.010429575042783834
        ]
      ]
    },
    {
      "seriesName": "INDKER",
      "seriesValues": [
        [
          2018,
          0.010554819563817918
        ],
        [
          2019,
          0.006913229032237619
        ],
        [
          2020,
          0.008390451623356521
        ],
        [
          2021,
          0.007348485900587075
        ],
        [
          2022,
          0.004274710085708663
        ],
        [
          2023,
          0.00406614436546643
        ],
        [
          2024,
          0.0034195789036905286
        ],
        [
          2025,
          0.003125302865888545
        ],
        [
          2026,
          0.0028512441241176113
        ],
        [
          2027,
          0.0025963870822156903
        ],
        [
          2028,
          0.0023583947163774376
        ],
        [
          2029,
          0.0021352816192599117
        ],
        [
          2030,
          0.00192662268481621
        ],
        [
          2031,
          0.001723039982660794
        ],
        [
          2032,
          0.001522906085154859
        ],
        [
          2033,
          0.0013549261092597408
        ],
        [
          2034,
          0.0011902324567707532
        ],
        [
          2035,
          0.001038095265648481
        ],
        [
          2036,
          0.0008981809394432434
        ],
        [
          2037,
          0.000763674876279453
        ],
        [
          2038,
          0.0006477123491801275
        ],
        [
          2039,
          0.0005429576174166953
        ],
        [
          2040,
          0.000448999315319318
        ],
        [
          2041,
          0.00036537950831028626
        ],
        [
          2042,
          0.000291683621874298
        ],
        [
          2043,
          0.00022747999820047247
        ],
        [
          2044,
          0.00017240422259261456
        ],
        [
          2045,
          0.00012585257361670175
        ],
        [
          2046,
          8.719554806216157e-05
        ],
        [
          2047,
          5.5859809587978296e-05
        ],
        [
          2048,
          3.158493865811024e-05
        ],
        [
          2049,
          1.2984640296381806e-05
        ],
        [
          2050,
          7.057906722132581e-07
        ],
        [
          2051,
          7.602353016636667e-07
        ]
      ]
    },
    {
      "seriesName": "INDLPG",
      "seriesValues": [
        [
          2018,
          0.003815680898468407
        ],
        [
          2019,
          0.0007000642468704189
        ],
        [
          2020,
          0.00064300497214727
        ],
        [
          2021,
          0.0006998733731597775
        ],
        [
          2022,
          0.00040857603912056433
        ],
        [
          2023,
          0.00038729275572037264
        ],
        [
          2024,
          0.00036695805246290665
        ],
        [
          2025,
          0.000347620502668275
        ],
        [
          2026,
          0.0003291717259470057
        ],
        [
          2027,
          0.0003115511764039223
        ],
        [
          2028,
          0.00029459188585522595
        ],
        [
          2029,
          0.00027812199891403156
        ],
        [
          2030,
          0.0002621436621793823
        ],
        [
          2031,
          0.0002465443476821059
        ],
        [
          2032,
          0.00023141528426307234
        ],
        [
          2033,
          0.00021670383215195184
        ],
        [
          2034,
          0.00020226274046349101
        ],
        [
          2035,
          0.00018816828022365456
        ],
        [
          2036,
          0.0001744339515347522
        ],
        [
          2037,
          0.0001610123580559109
        ],
        [
          2038,
          0.00014802018017336346
        ],
        [
          2039,
          0.00013544535880988446
        ],
        [
          2040,
          0.00012330346092784424
        ],
        [
          2041,
          0.000111590771447395
        ],
        [
          2042,
          0.00010033021485036169
        ],
        [
          2043,
          8.955755889198594e-05
        ],
        [
          2044,
          7.93430746309075e-05
        ],
        [
          2045,
          6.969314059704514e-05
        ],
        [
          2046,
          6.0605466176918425e-05
        ],
        [
          2047,
          5.209720372031416e-05
        ],
        [
          2048,
          4.414634182499429e-05
        ],
        [
          2049,
          3.682752236642145e-05
        ],
        [
          2050,
          3.0009783673434617e-05
        ],
        [
          2051,
          2.39096443320049e-05
        ]
      ]
    },
    {
      "seriesName": "INDBGS",
      "seriesValues": [
        [
          2019,
          0.0010870754550569724
        ],
        [
          2022,
          0.011725914296865324
        ],
        [
          2023,
          0.0272871212512075
        ],
        [
          2024,
          0.0236588002620368
        ],
        [
          2025,
          0.0288379429097507
        ],
        [
          2026,
          0.035621804463807
        ],
        [
          2027,
          0.0557226753633334
        ],
        [
          2028,
          0.0606726287976366
        ],
        [
          2029,
          0.0648171634833654
        ],
        [
          2030,
          0.0681982506740901
        ],
        [
          2031,
          0.0454575496467376
        ],
        [
          2032,
          0.0466812549910958
        ],
        [
          2033,
          0.047357372741901396
        ],
        [
          2034,
          0.0478584535024751
        ],
        [
          2035,
          0.0477804416760304
        ],
        [
          2036,
          0.0471660916050613
        ],
        [
          2037,
          0.0460130286624718
        ],
        [
          2038,
          0.0447672883242179
        ],
        [
          2039,
          0.0438581152840224
        ],
        [
          2040,
          0.0412867536014378
        ],
        [
          2041,
          0.0663664658934119
        ],
        [
          2042,
          0.0627314409292328
        ],
        [
          2043,
          0.058727101043489896
        ],
        [
          2044,
          0.054451373985918296
        ],
        [
          2045,
          0.0499599477966936
        ],
        [
          2046,
          0.0452999940253069
        ],
        [
          2047,
          0.040538545602523804
        ],
        [
          2048,
          0.019686339478673494
        ],
        [
          2049,
          0.01602255174915649
        ],
        [
          2050,
          0.013287423204592608
        ],
        [
          2051,
          0.010620425822921001
        ]
      ]
    },
    {
      "seriesName": "INDBDL",
      "seriesValues": [
        [
          2023,
          2.0527278719835554e-06
        ],
        [
          2024,
          2.0635355651050647e-06
        ],
        [
          2025,
          2.06977593792292e-06
        ],
        [
          2026,
          0.1054088936446931
        ],
        [
          2027,
          0.1175815056298189
        ],
        [
          2028,
          0.12802641851139
        ],
        [
          2029,
          0.1367718751899829
        ],
        [
          2030,
          0.1439063452776281
        ],
        [
          2031,
          0.1511906256488519
        ],
        [
          2032,
          0.1567660209253319
        ],
        [
          2033,
          0.1606620631053714
        ],
        [
          2034,
          0.1629157392305422
        ],
        [
          2035,
          0.1636207178080586
        ],
        [
          2036,
          0.1628550942752384
        ],
        [
          2037,
          0.1607022505427788
        ],
        [
          2038,
          0.157237022062502
        ],
        [
          2039,
          0.1525770289434248
        ],
        [
          2040,
          0.1468207319460725
        ],
        [
          2041,
          0.1400491506404442
        ],
        [
          2042,
          0.1323731808263488
        ],
        [
          2043,
          0.1239225377057409
        ],
        [
          2044,
          0.1148998113316379
        ],
        [
          2045,
          0.1054222246272801
        ],
        [
          2046,
          0.0955890580009601
        ],
        [
          2047,
          0.08554167373924271
        ],
        [
          2048,
          0.0754019994078435
        ],
        [
          2049,
          0.06536824596989241
        ],
        [
          2050,
          0.0555316012557253
        ],
        [
          2051,
          0.0444176588616074
        ]
      ]
    }
  ]
}