{
  "name": "mitigation_cb",
  "data": [
    {
      "seriesName": "DMD_TRA-F-HTRUCK",
      "seriesValues": [
        [
          2018,
          9.30287129068752
        ],
        [
          2019,
          9.26481584488577
        ],
        [
          2020,
          9.00569942192173
        ],
        [
          2021,
          9.30130222002481
        ],
        [
          2022,
          9.475192690207724
        ],
        [
          2023,
          10.65557080941241
        ],
        [
          2024,
          12.206548334666378
        ],
        [
          2025,
          12.584951336279737
        ],
        [
          2026,
          12.83665036288931
        ],
        [
          2027,
          13.093383370014918
        ],
        [
          2028,
          13.355251032138167
        ],
        [
          2029,
          13.6223560533805
        ],
        [
          2030,
          13.89480316218554
        ],
        [
          2031,
          14.21438364237508
        ],
        [
          2032,
          14.54131446673387
        ],
        [
          2033,
          14.875764700303693
        ],
        [
          2034,
          15.21790727684863
        ],
        [
          2035,
          15.567919155947049
        ],
        [
          2036,
          15.925981304759429
        ],
        [
          2037,
          16.29227881086944
        ],
        [
          2038,
          16.66700126023537
        ],
        [
          2039,
          17.050342322068012
        ],
        [
          2040,
          17.442500172140722
        ],
        [
          2041,
          17.843677720960258
        ],
        [
          2042,
          18.254082262003525
        ],
        [
          2043,
          18.673926146290544
        ],
        [
          2044,
          19.1034258420826
        ],
        [
          2045,
          19.5428053024193
        ],
        [
          2046,
          19.9922897963596
        ],
        [
          2047,
          20.4521124481601
        ],
        [
          2048,
          20.9225109783628
        ],
        [
          2049,
          21.4037287906272
        ],
        [
          2050,
          21.8960145534423
        ],
        [
          2051,
          22.3996228857027
        ]
      ]
    },
    {
      "seriesName": "DMD_TRA-F-LTRUCK",
      "seriesValues": [
        [
          2018,
          0.268813357263039
        ],
        [
          2019,
          0.2676447877407038
        ],
        [
          2020,
          0.26015935465082907
        ],
        [
          2021,
          0.2686988171739104
        ],
        [
          2022,
          0.27372221731805496
        ],
        [
          2023,
          0.3078213355669016
        ],
        [
          2024,
          0.35262644055483483
        ],
        [
          2025,
          0.3635578600283592
        ],
        [
          2026,
          0.3708290172247705
        ],
        [
          2027,
          0.37824559756470977
        ],
        [
          2028,
          0.3858105095368673
        ],
        [
          2029,
          0.3935267197430768
        ],
        [
          2030,
          0.40139725412462623
        ],
        [
          2031,
          0.4106293912895762
        ],
        [
          2032,
          0.4200738672959697
        ],
        [
          2033,
          0.4297355662471728
        ],
        [
          2034,
          0.4396194842757368
        ],
        [
          2035,
          0.4497307324277862
        ],
        [
          2036,
          0.46007453929158004
        ],
        [
          2037,
          0.4706562536842644
        ],
        [
          2038,
          0.48148134752265204
        ],
        [
          2039,
          0.4925554185127343
        ],
        [
          2040,
          0.5038841931457636
        ],
        [
          2041,
          0.5154735296108292
        ],
        [
          2042,
          0.5273294207882776
        ],
        [
          2043,
          0.5394579970333633
        ],
        [
          2044,
          0.5518655311689916
        ],
        [
          2045,
          0.5645584384868954
        ],
        [
          2046,
          0.5775432824216886
        ],
        [
          2047,
          0.5908267779186146
        ],
        [
          2048,
          0.6044157937631813
        ],
        [
          2049,
          0.6183173569519888
        ],
        [
          2050,
          0.6325386560671471
        ],
        [
          2051,
          0.6470870453648995
        ]
      ]
    },
    {
      "seriesName": "DMD_TRA-F-MTRUCK",
      "seriesValues": [
        [
          2018,
          1.0494597219344
        ],
        [
          2019,
          1.0451043975464025
        ],
        [
          2020,
          1.0158751375757569
        ],
        [
          2021,
          1.0492201914622552
        ],
        [
          2022,
          1.068835658769252
        ],
        [
          2023,
          1.201986536129494
        ],
        [
          2024,
          1.376942354260986
        ],
        [
          2025,
          1.419627568296627
        ],
        [
          2026,
          1.448020120021814
        ],
        [
          2027,
          1.4769805223931813
        ],
        [
          2028,
          1.5065201327345392
        ],
        [
          2029,
          1.536650535275624
        ],
        [
          2030,
          1.5673835446447981
        ],
        [
          2031,
          1.603433366922635
        ],
        [
          2032,
          1.640312334262096
        ],
        [
          2033,
          1.678039516080728
        ],
        [
          2034,
          1.716634425113947
        ],
        [
          2035,
          1.7561170169547167
        ],
        [
          2036,
          1.7965077085056285
        ],
        [
          2037,
          1.8378273856154208
        ],
        [
          2038,
          1.8800974152186902
        ],
        [
          2039,
          1.9233396557088278
        ],
        [
          2040,
          1.9675764675079543
        ],
        [
          2041,
          2.0128307259783
        ],
        [
          2042,
          2.0591258326655355
        ],
        [
          2043,
          2.1064857319310777
        ],
        [
          2044,
          2.1549349008379908
        ],
        [
          2045,
          2.2044984004599972
        ],
        [
          2046,
          2.255201861957824
        ],
        [
          2047,
          2.3070715047756174
        ],
        [
          2048,
          2.360134147659001
        ],
        [
          2049,
          2.414417234139645
        ],
        [
          2050,
          2.46994882787848
        ],
        [
          2051,
          2.5267576498467
        ]
      ]
    },
    {
      "seriesName": "DMD_TRA-F-TRAIN",
      "seriesValues": [
        [
          2018,
          0.0814467187970796
        ],
        [
          2019,
          0.0610351304838802
        ],
        [
          2020,
          0.0664662430603933
        ],
        [
          2021,
          0.0593288337052859
        ],
        [
          2022,
          0.0604380012976089
        ],
        [
          2023,
          0.06796709498566819
        ],
        [
          2024,
          0.0778600729077272
        ],
        [
          2025,
          0.0802737331135268
        ],
        [
          2026,
          0.0818792061341587
        ],
        [
          2027,
          0.0835167887677472
        ],
        [
          2028,
          0.0851871231420466
        ],
        [
          2029,
          0.0868908642829361
        ],
        [
          2030,
          0.0886287415244912
        ],
        [
          2031,
          0.0906671932317282
        ],
        [
          2032,
          0.0927525354500301
        ],
        [
          2033,
          0.094885840955075
        ],
        [
          2034,
          0.0970682133041407
        ],
        [
          2035,
          0.0993007771877553
        ],
        [
          2036,
          0.101584680952258
        ],
        [
          2037,
          0.103921139200767
        ],
        [
          2038,
          0.106311315039119
        ],
        [
          2039,
          0.108756492319721
        ],
        [
          2040,
          0.111257873566442
        ],
        [
          2041,
          0.113816816561189
        ],
        [
          2042,
          0.11643458404199
        ],
        [
          2043,
          0.119113067112148
        ],
        [
          2044,
          0.121852234392553
        ],
        [
          2045,
          0.124654709557425
        ],
        [
          2046,
          0.127521824284234
        ],
        [
          2047,
          0.130454814572976
        ],
        [
          2048,
          0.133455225148117
        ],
        [
          2049,
          0.136524740972488
        ],
        [
          2050,
          0.139664804952103
        ],
        [
          2051,
          0.142877090215055
        ]
      ]
    }
  ]
}